[
    {
        "sol_41": [
            {
                "cost": "8.586875472154492"
            },
            {
                "responseTime": "39.01747272605359"
            },
            {
                "reliability": "0.998079470511289"
            }
        ]
    },
    {
        "sol_85": [
            {
                "cost": "8.383460866541991"
            },
            {
                "responseTime": "37.28153871619004"
            },
            {
                "reliability": "0.9964406578571289"
            }
        ]
    },
    {
        "sol_42": [
            {
                "cost": "8.6240001486"
            },
            {
                "responseTime": "34.02549889264"
            },
            {
                "reliability": "0.9983515326799999"
            }
        ]
    },
    {
        "sol_86": [
            {
                "cost": "8.519018774231835"
            },
            {
                "responseTime": "34.65157935420032"
            },
            {
                "reliability": "0.9965084570162069"
            }
        ]
    },
    {
        "sol_43": [
            {
                "cost": "9.301419757722462"
            },
            {
                "responseTime": "30.729239884088592"
            },
            {
                "reliability": "0.9983956730601952"
            }
        ]
    },
    {
        "sol_87": [
            {
                "cost": "8.397132832812499"
            },
            {
                "responseTime": "29.6209860008965"
            },
            {
                "reliability": "0.99661748356925"
            }
        ]
    },
    {
        "sol_44": [
            {
                "cost": "8.879186539149416"
            },
            {
                "responseTime": "36.79534435766953"
            },
            {
                "reliability": "0.9982902577716796"
            }
        ]
    },
    {
        "sol_88": [
            {
                "cost": "8.92515315779082"
            },
            {
                "responseTime": "28.85345924149071"
            },
            {
                "reliability": "0.9966270065721835"
            }
        ]
    },
    {
        "sol_81": [
            {
                "cost": "8.653384740493749"
            },
            {
                "responseTime": "40.21271784696625"
            },
            {
                "reliability": "0.9963300823606249"
            }
        ]
    },
    {
        "sol_82": [
            {
                "cost": "8.3679285642"
            },
            {
                "responseTime": "42.68191487108"
            },
            {
                "reliability": "0.99597452746"
            }
        ]
    },
    {
        "sol_83": [
            {
                "cost": "8.090994988023631"
            },
            {
                "responseTime": "39.5022550364784"
            },
            {
                "reliability": "0.9961797676914649"
            }
        ]
    },
    {
        "sol_40": [
            {
                "cost": "8.8638859392"
            },
            {
                "responseTime": "42.19797124608"
            },
            {
                "reliability": "0.9979034649599998"
            }
        ]
    },
    {
        "sol_84": [
            {
                "cost": "8.805836451325977"
            },
            {
                "responseTime": "31.21654748797043"
            },
            {
                "reliability": "0.9965862805431054"
            }
        ]
    },
    {
        "sol_80": [
            {
                "cost": "9.0727828907875"
            },
            {
                "responseTime": "33.8178456973275"
            },
            {
                "reliability": "0.99652316939875"
            }
        ]
    },
    {
        "sol_49": [
            {
                "cost": "8.708624946859375"
            },
            {
                "responseTime": "37.403493897749996"
            },
            {
                "reliability": "0.9985431986"
            }
        ]
    },
    {
        "sol_45": [
            {
                "cost": "9.42068495371043"
            },
            {
                "responseTime": "28.365775821459962"
            },
            {
                "reliability": "0.9984227056174764"
            }
        ]
    },
    {
        "sol_89": [
            {
                "cost": "8.241838758250976"
            },
            {
                "responseTime": "36.66611788021618"
            },
            {
                "reliability": "0.996303630799293"
            }
        ]
    },
    {
        "sol_46": [
            {
                "cost": "9.44761414445625"
            },
            {
                "responseTime": "28.094005126413748"
            },
            {
                "reliability": "0.996636142699375"
            }
        ]
    },
    {
        "sol_47": [
            {
                "cost": "8.7934433243"
            },
            {
                "responseTime": "26.437031928959996"
            },
            {
                "reliability": "0.9994251401600001"
            }
        ]
    },
    {
        "sol_48": [
            {
                "cost": "9.47077421815127"
            },
            {
                "responseTime": "23.140138111534064"
            },
            {
                "reliability": "0.9994532832606251"
            }
        ]
    },
    {
        "sol_52": [
            {
                "cost": "9.318845239965626"
            },
            {
                "responseTime": "32.14045217289"
            },
            {
                "reliability": "0.99931641184"
            }
        ]
    },
    {
        "sol_53": [
            {
                "cost": "9.033814041600001"
            },
            {
                "responseTime": "34.61388805631999"
            },
            {
                "reliability": "0.99906757632"
            }
        ]
    },
    {
        "sol_10": [
            {
                "cost": "9.59232303"
            },
            {
                "responseTime": "20.716168957679997"
            },
            {
                "reliability": "0.99997024384"
            }
        ]
    },
    {
        "sol_54": [
            {
                "cost": "8.042278782531248"
            },
            {
                "responseTime": "45.46544761041875"
            },
            {
                "reliability": "0.995317971821875"
            }
        ]
    },
    {
        "sol_11": [
            {
                "cost": "10.269554284474609"
            },
            {
                "responseTime": "17.419036934865076"
            },
            {
                "reliability": "0.9999816218721874"
            }
        ]
    },
    {
        "sol_55": [
            {
                "cost": "8.756661498183693"
            },
            {
                "responseTime": "31.431920099097184"
            },
            {
                "reliability": "0.9992164456831251"
            }
        ]
    },
    {
        "sol_50": [
            {
                "cost": "9.495302427465624"
            },
            {
                "responseTime": "27.699612954139994"
            },
            {
                "reliability": "0.9993164118400001"
            }
        ]
    },
    {
        "sol_51": [
            {
                "cost": "9.7378783243"
            },
            {
                "responseTime": "25.742594428959997"
            },
            {
                "reliability": "0.9994251401600001"
            }
        ]
    },
    {
        "sol_16": [
            {
                "cost": "9.706518881182735"
            },
            {
                "responseTime": "22.8741802006027"
            },
            {
                "reliability": "0.9998971414211875"
            }
        ]
    },
    {
        "sol_17": [
            {
                "cost": "9.014685387049884"
            },
            {
                "responseTime": "34.164907455280904"
            },
            {
                "reliability": "0.9983408793964608"
            }
        ]
    },
    {
        "sol_18": [
            {
                "cost": "8.868606753831251"
            },
            {
                "responseTime": "28.6304400756325"
            },
            {
                "reliability": "0.99348016809"
            }
        ]
    },
    {
        "sol_19": [
            {
                "cost": "7.46295198565625"
            },
            {
                "responseTime": "45.9943122002625"
            },
            {
                "reliability": "0.9919111456499999"
            }
        ]
    },
    {
        "sol_12": [
            {
                "cost": "9.847731932603518"
            },
            {
                "responseTime": "23.48710474496367"
            },
            {
                "reliability": "0.9999482255078125"
            }
        ]
    },
    {
        "sol_56": [
            {
                "cost": "9.048730618522951"
            },
            {
                "responseTime": "29.207653029370313"
            },
            {
                "reliability": "0.999382239946875"
            }
        ]
    },
    {
        "sol_13": [
            {
                "cost": "9.555980699669922"
            },
            {
                "responseTime": "25.71234539610914"
            },
            {
                "reliability": "0.9998396658184375"
            }
        ]
    },
    {
        "sol_57": [
            {
                "cost": "9.18414773443834"
            },
            {
                "responseTime": "26.57658322770206"
            },
            {
                "reliability": "0.999417962542375"
            }
        ]
    },
    {
        "sol_14": [
            {
                "cost": "9.983049916466328"
            },
            {
                "responseTime": "20.855776308687233"
            },
            {
                "reliability": "0.9999668887105625"
            }
        ]
    },
    {
        "sol_58": [
            {
                "cost": "9.06198380018"
            },
            {
                "responseTime": "21.543964951295997"
            },
            {
                "reliability": "0.999465524416"
            }
        ]
    },
    {
        "sol_15": [
            {
                "cost": "10.38869061331242"
            },
            {
                "responseTime": "15.054995729093637"
            },
            {
                "reliability": "0.9999864281749374"
            }
        ]
    },
    {
        "sol_59": [
            {
                "cost": "9.58997644938541"
            },
            {
                "responseTime": "20.77624652959581"
            },
            {
                "reliability": "0.999469039056125"
            }
        ]
    },
    {
        "sol_7": [
            {
                "cost": "10.536758030000001"
            },
            {
                "responseTime": "20.02173145768"
            },
            {
                "reliability": "0.99997024384"
            }
        ]
    },
    {
        "sol_63": [
            {
                "cost": "10.495709367209376"
            },
            {
                "responseTime": "20.06178821706125"
            },
            {
                "reliability": "0.9998261803893751"
            }
        ]
    },
    {
        "sol_8": [
            {
                "cost": "9.833331328000002"
            },
            {
                "responseTime": "28.895048309759996"
            },
            {
                "reliability": "0.99972871168"
            }
        ]
    },
    {
        "sol_20": [
            {
                "cost": "8.25062624049375"
            },
            {
                "responseTime": "36.30527846024749"
            },
            {
                "reliability": "0.9930707444699999"
            }
        ]
    },
    {
        "sol_64": [
            {
                "cost": "9.17682731891875"
            },
            {
                "responseTime": "26.4824153665225"
            },
            {
                "reliability": "0.99979467037875"
            }
        ]
    },
    {
        "sol_9": [
            {
                "cost": "9.72944854528"
            },
            {
                "responseTime": "18.216315336192"
            },
            {
                "reliability": "0.9999799306239999"
            }
        ]
    },
    {
        "sol_21": [
            {
                "cost": "8.493670898600001"
            },
            {
                "responseTime": "34.35291814264"
            },
            {
                "reliability": "0.99332040768"
            }
        ]
    },
    {
        "sol_65": [
            {
                "cost": "9.092413183171875"
            },
            {
                "responseTime": "37.45007696415625"
            },
            {
                "reliability": "0.999006792271875"
            }
        ]
    },
    {
        "sol_22": [
            {
                "cost": "8.074169052993751"
            },
            {
                "responseTime": "40.7461176789975"
            },
            {
                "reliability": "0.99307074447"
            }
        ]
    },
    {
        "sol_66": [
            {
                "cost": "9.878799085690625"
            },
            {
                "responseTime": "27.745281935608748"
            },
            {
                "reliability": "0.999708189230625"
            }
        ]
    },
    {
        "sol_60": [
            {
                "cost": "8.907339294936582"
            },
            {
                "responseTime": "28.594211518248933"
            },
            {
                "reliability": "0.999299567678625"
            }
        ]
    },
    {
        "sol_61": [
            {
                "cost": "8.930650170240002"
            },
            {
                "responseTime": "23.937373913088003"
            },
            {
                "reliability": "0.999448531968"
            }
        ]
    },
    {
        "sol_62": [
            {
                "cost": "9.313996988547501"
            },
            {
                "responseTime": "23.982667968073"
            },
            {
                "reliability": "0.9998111147955"
            }
        ]
    },
    {
        "sol_0": [
            {
                "cost": "9.8607133924"
            },
            {
                "responseTime": "15.822748702608"
            },
            {
                "reliability": "0.999985468544"
            }
        ]
    },
    {
        "sol_1": [
            {
                "cost": "8.76127888872"
            },
            {
                "responseTime": "31.526358396672002"
            },
            {
                "reliability": "0.9983878988639998"
            }
        ]
    },
    {
        "sol_2": [
            {
                "cost": "10.112410373821875"
            },
            {
                "responseTime": "20.01660645853"
            },
            {
                "reliability": "0.9994723162800001"
            }
        ]
    },
    {
        "sol_3": [
            {
                "cost": "10.9111097633125"
            },
            {
                "responseTime": "14.295322809827496"
            },
            {
                "reliability": "0.99998726287"
            }
        ]
    },
    {
        "sol_4": [
            {
                "cost": "9.508610165562501"
            },
            {
                "responseTime": "31.6868763732375"
            },
            {
                "reliability": "0.99930242755"
            }
        ]
    },
    {
        "sol_5": [
            {
                "cost": "10.117992548437499"
            },
            {
                "responseTime": "26.4203219727825"
            },
            {
                "reliability": "0.99990817361"
            }
        ]
    },
    {
        "sol_6": [
            {
                "cost": "10.2944497359375"
            },
            {
                "responseTime": "21.9794827540325"
            },
            {
                "reliability": "0.99990817361"
            }
        ]
    },
    {
        "sol_27": [
            {
                "cost": "7.804295960536134"
            },
            {
                "responseTime": "37.81581760840196"
            },
            {
                "reliability": "0.9932109248859375"
            }
        ]
    },
    {
        "sol_28": [
            {
                "cost": "7.511733487291211"
            },
            {
                "responseTime": "40.034682109110236"
            },
            {
                "reliability": "0.9928880304478125"
            }
        ]
    },
    {
        "sol_29": [
            {
                "cost": "7.9398961380841016"
            },
            {
                "responseTime": "35.18649954042989"
            },
            {
                "reliability": "0.9933005032261875"
            }
        ]
    },
    {
        "sol_23": [
            {
                "cost": "7.788629939200001"
            },
            {
                "responseTime": "43.213267246079994"
            },
            {
                "reliability": "0.9926474649599999"
            }
        ]
    },
    {
        "sol_67": [
            {
                "cost": "10.12126231891875"
            },
            {
                "responseTime": "25.7879778665225"
            },
            {
                "reliability": "0.99979467037875"
            }
        ]
    },
    {
        "sol_24": [
            {
                "cost": "7.662613405064179"
            },
            {
                "responseTime": "37.19933091992817"
            },
            {
                "reliability": "0.9930380412680624"
            }
        ]
    },
    {
        "sol_68": [
            {
                "cost": "9.702341898190626"
            },
            {
                "responseTime": "32.18612115435875"
            },
            {
                "reliability": "0.999708189230625"
            }
        ]
    },
    {
        "sol_25": [
            {
                "cost": "7.5492358986"
            },
            {
                "responseTime": "35.04735564264"
            },
            {
                "reliability": "0.99332040768"
            }
        ]
    },
    {
        "sol_69": [
            {
                "cost": "9.4174492769"
            },
            {
                "responseTime": "34.65995007532"
            },
            {
                "reliability": "0.99949011882"
            }
        ]
    },
    {
        "sol_26": [
            {
                "cost": "8.22677743692168"
            },
            {
                "responseTime": "31.752336022028047"
            },
            {
                "reliability": "0.9934080391490625"
            }
        ]
    },
    {
        "sol_30": [
            {
                "cost": "7.81810502236"
            },
            {
                "responseTime": "30.157170259824"
            },
            {
                "reliability": "0.9934528596479999"
            }
        ]
    },
    {
        "sol_74": [
            {
                "cost": "9.445297728401249"
            },
            {
                "responseTime": "21.5891814914135"
            },
            {
                "reliability": "0.99982208791725"
            }
        ]
    },
    {
        "sol_31": [
            {
                "cost": "8.346135599932149"
            },
            {
                "responseTime": "29.389770118690983"
            },
            {
                "reliability": "0.9934667491093124"
            }
        ]
    },
    {
        "sol_75": [
            {
                "cost": "9.973282789073183"
            },
            {
                "responseTime": "20.821445366959132"
            },
            {
                "reliability": "0.9998242285389961"
            }
        ]
    },
    {
        "sol_32": [
            {
                "cost": "7.68661264768"
            },
            {
                "responseTime": "32.549217434111995"
            },
            {
                "reliability": "0.9933919242239999"
            }
        ]
    },
    {
        "sol_76": [
            {
                "cost": "9.290848745654042"
            },
            {
                "responseTime": "28.639914592544287"
            },
            {
                "reliability": "0.9996940070048554"
            }
        ]
    },
    {
        "sol_33": [
            {
                "cost": "8.73765670765496"
            },
            {
                "responseTime": "36.18073070670496"
            },
            {
                "reliability": "0.9981820031160702"
            }
        ]
    },
    {
        "sol_77": [
            {
                "cost": "8.265682186275"
            },
            {
                "responseTime": "32.013566299067"
            },
            {
                "reliability": "0.9965748829315"
            }
        ]
    },
    {
        "sol_70": [
            {
                "cost": "9.14022465161709"
            },
            {
                "responseTime": "31.47777076896144"
            },
            {
                "reliability": "0.9996224236767774"
            }
        ]
    },
    {
        "sol_71": [
            {
                "cost": "9.854112423004981"
            },
            {
                "responseTime": "23.18541173512879"
            },
            {
                "reliability": "0.999814279029668"
            }
        ]
    },
    {
        "sol_72": [
            {
                "cost": "9.432167412104004"
            },
            {
                "responseTime": "29.253167244482615"
            },
            {
                "reliability": "0.9997619488555665"
            }
        ]
    },
    {
        "sol_73": [
            {
                "cost": "9.567541720172208"
            },
            {
                "responseTime": "26.62199104638296"
            },
            {
                "reliability": "0.9997893891148946"
            }
        ]
    },
    {
        "sol_38": [
            {
                "cost": "9.5684351486"
            },
            {
                "responseTime": "33.33106139264"
            },
            {
                "reliability": "0.9983515326799999"
            }
        ]
    },
    {
        "sol_39": [
            {
                "cost": "9.14918710768125"
            },
            {
                "responseTime": "39.727188077435"
            },
            {
                "reliability": "0.9982033968137498"
            }
        ]
    },
    {
        "sol_34": [
            {
                "cost": "9.943133589768749"
            },
            {
                "responseTime": "27.606233208444998"
            },
            {
                "reliability": "0.9984286094962498"
            }
        ]
    },
    {
        "sol_78": [
            {
                "cost": "8.128347890787499"
            },
            {
                "responseTime": "34.5122831973275"
            },
            {
                "reliability": "0.99652316939875"
            }
        ]
    },
    {
        "sol_35": [
            {
                "cost": "8.892677191239999"
            },
            {
                "responseTime": "29.133393203744"
            },
            {
                "reliability": "0.9984164895279999"
            }
        ]
    },
    {
        "sol_79": [
            {
                "cost": "8.82984192799375"
            },
            {
                "responseTime": "35.77187862821625"
            },
            {
                "reliability": "0.9963300823606249"
            }
        ]
    },
    {
        "sol_36": [
            {
                "cost": "8.53837100909375"
            },
            {
                "responseTime": "44.983488489325"
            },
            {
                "reliability": "0.9973144464312499"
            }
        ]
    },
    {
        "sol_37": [
            {
                "cost": "9.325644295181249"
            },
            {
                "responseTime": "35.286348858685"
            },
            {
                "reliability": "0.9982033968137498"
            }
        ]
    }
]